ms_pkg/__init__.py
ms_pkg/mypackage.py
ms_pkg-0.0.1.dist-info/METADATA
ms_pkg-0.0.1.dist-info/WHEEL
ms_pkg-0.0.1.dist-info/top_level.txt
ms_pkg-0.0.1.dist-info/RECORD
