Metadata-Version: 2.1
Name: ms-pkg
Version: 0.0.1
Summary: My first PyPI package
Home-page: UNKNOWN
Author: UNKNOWN
Author-email: UNKNOWN
License: UNKNOWN
Platform: UNKNOWN
